bubot_auth_service/__init__.py
bubot_auth_service/buject/__init__.py
bubot_auth_service/buject/OcfDevice/subtype/AuthService/AuthService.json
bubot_auth_service/buject/OcfDevice/subtype/AuthService/AuthService.orx.json
bubot_auth_service/buject/OcfDevice/subtype/AuthService/AuthService.py
bubot_auth_service/buject/OcfDevice/subtype/AuthService/AuthServiceApi.py
bubot_auth_service/buject/OcfDevice/subtype/AuthService/__init__.py
bubot_auth_service/buject/OcfDevice/subtype/AuthService/i18n/cn.json
bubot_auth_service/buject/OcfDevice/subtype/AuthService/i18n/en.json
bubot_auth_service/buject/OcfDevice/subtype/AuthService/i18n/ru.json
bubot_auth_service/buject/OcfDevice/subtype/AuthService/models/ExtException.v1.json
bubot_auth_service/buject/OcfDevice/subtype/AuthService/models/Session.v1.json
bubot_auth_service/buject/OcfDevice/subtype/AuthService/models/User.v1.json
bubot_auth_service/buject/OcfDevice/subtype/AuthService/reference/AuthService.v1.json
bubot_auth_service/buject/OcfDevice/subtype/AuthService/static/ui/index.html
bubot_auth_service/buject/OcfDevice/subtype/AuthService/static/ui/css/chunk-2a0f19ce.14a7ef2c.css
bubot_auth_service/buject/OcfDevice/subtype/AuthService/static/ui/css/chunk-2f210fe1.1a5b56c8.css
bubot_auth_service/buject/OcfDevice/subtype/AuthService/static/ui/css/chunk-357bd036.c5da7388.css
bubot_auth_service/buject/OcfDevice/subtype/AuthService/static/ui/css/chunk-38ccf0e4.14a7ef2c.css
bubot_auth_service/buject/OcfDevice/subtype/AuthService/static/ui/css/chunk-3bc313e3.1a5b56c8.css
bubot_auth_service/buject/OcfDevice/subtype/AuthService/static/ui/css/chunk-3fc8deba.14a7ef2c.css
bubot_auth_service/buject/OcfDevice/subtype/AuthService/static/ui/css/chunk-4578c45e.ad28204c.css
bubot_auth_service/buject/OcfDevice/subtype/AuthService/static/ui/css/chunk-482d68f6.16a44419.css
bubot_auth_service/buject/OcfDevice/subtype/AuthService/static/ui/css/chunk-5235469a.0d4b3a49.css
Bubot_AuthService-4.1.0.dist-info/LICENSE
Bubot_AuthService-4.1.0.dist-info/METADATA
Bubot_AuthService-4.1.0.dist-info/WHEEL
Bubot_AuthService-4.1.0.dist-info/top_level.txt
Bubot_AuthService-4.1.0.dist-info/RECORD
