Metadata-Version: 2.1
Name: Bubot_AuthService
Version: 4.1.0
Summary: Service providing authentication capabilities for the Bubot framework
Home-page: https://github.com/businka/Bubot_AuthService
Author: Razgovorov Mikhail
Author-email: 1338833@gmail.com
Classifier: Programming Language :: Python :: 3
Classifier: License :: OSI Approved :: MIT License
Classifier: Operating System :: OS Independent
Classifier: Development Status :: 3 - Alpha
Classifier: Framework :: AsyncIO
Requires-Python: >=3.7
License-File: LICENSE
Requires-Dist: Bubot_WebServer>=4.1.0
Requires-Dist: Bubot_Core>=4.1.0
